README.rst
setup.py
lamastats/GeoIP.dat
lamastats/__init__.py
lamastats/lamastats.py
lamastats.egg-info/PKG-INFO
lamastats.egg-info/SOURCES.txt
lamastats.egg-info/dependency_links.txt
lamastats.egg-info/entry_points.txt
lamastats.egg-info/requires.txt
lamastats.egg-info/top_level.txt